skymantle_mock_data_forge/__init__.py
skymantle_mock_data_forge/base_forge.py
skymantle_mock_data_forge/dynamodb_forge.py
skymantle_mock_data_forge/forge_factory.py
skymantle_mock_data_forge/models.py
skymantle_mock_data_forge/s3_forge.py
skymantle_mock_data_forge-0.4.0.dist-info/METADATA
skymantle_mock_data_forge-0.4.0.dist-info/WHEEL
skymantle_mock_data_forge-0.4.0.dist-info/licenses/LICENSE
skymantle_mock_data_forge-0.4.0.dist-info/RECORD
