Metadata-Version: 2.3
Name: skymantle_mock_data_forge
Version: 0.4.0
Summary: A library for deploying test data to aws resources when running integration and end-to-end tests.
Project-URL: Home, https://github.com/skymantle-tech/skymantle-mock-data-forge
Project-URL: Issues, https://github.com/skymantle-tech/skymantle-mock-data-forge/issues
Author-email: Artin Yong-Bannayan <ayongbannayan@skymantle.com>
License:                                  Apache License
License-File: LICENSE
Classifier: Development Status :: 4 - Beta
Classifier: Intended Audience :: Developers
Classifier: License :: OSI Approved :: Apache Software License
Classifier: Programming Language :: Python
Classifier: Topic :: Software Development :: Testing
Requires-Python: >=3.11
Requires-Dist: skymantle-boto-buddy[boto]
